nbresuse/__init__.py
nbresuse/api.py
nbresuse/config.py
nbresuse/metrics.py
nbresuse/prometheus.py
nbresuse/utils.py
nbresuse/etc/nbextension.json
nbresuse/etc/serverextension.json
nbresuse/static/main.js
nbresuse/tests/__init__.py
nbresuse/tests/test_basic.py
nbresuse-0.4.0.data/data/etc/jupyter/jupyter_notebook_config.d/serverextension.json
nbresuse-0.4.0.data/data/etc/jupyter/nbconfig/notebook.d/nbextension.json
nbresuse-0.4.0.data/data/share/jupyter/nbextensions/nbresuse/main.js
nbresuse-0.4.0.dist-info/LICENSE
nbresuse-0.4.0.dist-info/METADATA
nbresuse-0.4.0.dist-info/WHEEL
nbresuse-0.4.0.dist-info/top_level.txt
nbresuse-0.4.0.dist-info/RECORD
