Metadata-Version: 2.1
Name: nbresuse
Version: 0.4.0
Summary: Simple Jupyter extension to show how much resources (RAM) your notebook is using
Home-page: https://github.com/yuvipanda/nbresuse
Author: Yuvi Panda
License: BSD
Platform: UNKNOWN
Classifier: License :: OSI Approved :: BSD License
Classifier: Programming Language :: Python :: 3
Requires-Dist: notebook (>=5.6.0)
Requires-Dist: prometheus-client
Requires-Dist: psutil (>=5.6.0)
Provides-Extra: dev
Requires-Dist: autopep8 ; extra == 'dev'
Requires-Dist: black ; extra == 'dev'
Requires-Dist: pytest ; extra == 'dev'
Requires-Dist: flake8 ; extra == 'dev'
Requires-Dist: pytest-cov (>=2.6.1) ; extra == 'dev'
Requires-Dist: mock ; extra == 'dev'
